adafruit_us100.py
adafruit_circuitpython_us100-1.1.21.dist-info/licenses/LICENSE
adafruit_circuitpython_us100-1.1.21.dist-info/METADATA
adafruit_circuitpython_us100-1.1.21.dist-info/WHEEL
adafruit_circuitpython_us100-1.1.21.dist-info/top_level.txt
adafruit_circuitpython_us100-1.1.21.dist-info/RECORD
