Metadata-Version: 2.4
Name: adafruit-circuitpython-us100
Version: 1.1.21
Summary: CircuitPython library for reading distance and temperature via US-100 ultra-sonic sensor.
Author-email: Adafruit Industries <circuitpython@adafruit.com>
License: MIT
Project-URL: Homepage, https://github.com/adafruit/Adafruit_CircuitPython_US100
Keywords: adafruit,us100,temperature,temp,distance,sensor,ultra-sonic,hardware,micropython,circuitpython
Classifier: Intended Audience :: Developers
Classifier: Topic :: Software Development :: Libraries
Classifier: Topic :: Software Development :: Embedded Systems
Classifier: Topic :: System :: Hardware
Classifier: License :: OSI Approved :: MIT License
Classifier: Programming Language :: Python :: 3
License-File: LICENSE
Requires-Dist: Adafruit-Blinka
Requires-Dist: pyserial
Provides-Extra: optional
Dynamic: license-file
